<annotation>
	<folder>thumbsdown</folder>
	<filename>thumbsdown.20baa980-b871-11eb-96f6-0c7a15e4a3f8.jpg</filename>
	<path>D:\ML\TFODCourse\Tensorflow\workspace\images\collectedimages\thumbsdown\thumbsdown.20baa980-b871-11eb-96f6-0c7a15e4a3f8.jpg</path>
	<source>
		<database>Unknown</database>
	</source>
	<size>
		<width>640</width>
		<height>480</height>
		<depth>3</depth>
	</size>
	<segmented>0</segmented>
	<object>
		<name>ThumbsDown</name>
		<pose>Unspecified</pose>
		<truncated>0</truncated>
		<difficult>0</difficult>
		<bndbox>
			<xmin>516</xmin>
			<ymin>67</ymin>
			<xmax>627</xmax>
			<ymax>211</ymax>
		</bndbox>
	</object>
</annotation>
