<annotation>
	<folder>thumbsdown</folder>
	<filename>thumbsdown.3ac81d49-b882-11eb-97b2-b42e99f32e01.jpg</filename>
	<path>D:\TF\Tensorflow\workspace\images\collectedimages\thumbsdown\thumbsdown.3ac81d49-b882-11eb-97b2-b42e99f32e01.jpg</path>
	<source>
		<database>Unknown</database>
	</source>
	<size>
		<width>640</width>
		<height>480</height>
		<depth>3</depth>
	</size>
	<segmented>0</segmented>
	<object>
		<name>ThumbsDown</name>
		<pose>Unspecified</pose>
		<truncated>0</truncated>
		<difficult>0</difficult>
		<bndbox>
			<xmin>102</xmin>
			<ymin>221</ymin>
			<xmax>259</xmax>
			<ymax>452</ymax>
		</bndbox>
	</object>
</annotation>
