<annotation>
	<folder>thumbsdown</folder>
	<filename>thumbsdown.603a5942-b8a5-11eb-ba90-b42e99f32e01.jpg</filename>
	<path>D:\TF\Tensorflow\workspace\images\collectedimages\thumbsdown\thumbsdown.603a5942-b8a5-11eb-ba90-b42e99f32e01.jpg</path>
	<source>
		<database>Unknown</database>
	</source>
	<size>
		<width>1600</width>
		<height>900</height>
		<depth>3</depth>
	</size>
	<segmented>0</segmented>
	<object>
		<name>ThumbsDown</name>
		<pose>Unspecified</pose>
		<truncated>0</truncated>
		<difficult>0</difficult>
		<bndbox>
			<xmin>392</xmin>
			<ymin>260</ymin>
			<xmax>660</xmax>
			<ymax>650</ymax>
		</bndbox>
	</object>
</annotation>
